cell_neighbors/__init__.py
cell_neighbors/__version__.py
cell_neighbors/_knn.py
cell_neighbors-0.2.0.dist-info/METADATA
cell_neighbors-0.2.0.dist-info/WHEEL
cell_neighbors-0.2.0.dist-info/RECORD
