Metadata-Version: 2.4
Name: cell-neighbors
Version: 0.2.0
Summary: voyager-based kNN for single-cell data
Requires-Python: >=3.11
Requires-Dist: adata-query>=0.2.1
Requires-Dist: anndata
Requires-Dist: pandas
Requires-Dist: scanpy
Requires-Dist: voyager
